{
  "id": 2408,
  "name": "DR.ANMYTAS IR3",
  "slug": "ir3",
  "parent": 0,
  "type": "simple",
  "variation": "",
  "permalink": "https://dranmytas.com/product/ir3/",
  "sku": "",
  "short_description": "<p>Dịu nhẹ và an toàn như vòng tay của mẹ, Dr.Anmytas IR3 bảo vệ da bé tối đa khỏi tia UVA, UVB, IR, HEVL bằng công thức chống nắng vật lý an toàn, không chất hóa học gây độc hại đến cơ thể bé yêu</p>",
  "description": "<h2>NGUỒN GỐC NGUYÊN LIỆU CHÍNH</h2>\n<ul>\n<li>Từ The Innovation Company &#8211; Pháp</li>\n</ul>\n<h2>ƯU ĐIỂM SẢN PHẨM:</h2>\n<ul>\n<li>AN TOÀN VỚI LÀN DA TRẺ NHỎ</li>\n<li>Màng lọc chống nắng vật lý: TiO2 + ZnO</li>\n<li>Chỉ số chống nắng: SPF50+/PA++++</li>\n<li>Chống 4 tia: UVA/UVB/HEVL/IR-A</li>\n<li>Chỉ số nâng tone: 4/10</li>\n</ul>\n<h2>LỢI ÍCH:</h2>\n<p>Làn da của trẻ có lớp thượng bì mỏng hơn 30-40% so với người lớn nên rất dễ bị tổn thương bởi ánh nắng mặt trời.</p>\n<p>Làn da của trẻ không được bảo vệ từ nhỏ có thể tăng nguy cơ mắc các bệnh lý về da và dễ lão hóa khi trưởng thành.</p>\n<p>Kem chống nắng hóa học chứa các thành phần như Oxy- benzone, Octinoxate, Homosalate&#8230; gây hại đến cơ thể: rối loạn hoocmoon, tích tụ độc tính và có thể gây u hạt/ung thư&#8230; Những hoạt chất này đã bị cấm tại một số nước.</p>\n<h2>1. Bảo vệ da đa chiều, chống 4 loại tia mạnh mẽ</h2>\n<p>Sự kết hợp công nghệ chống nắng kép giữa màng lọc vật lý và hóa học tiên tiến, mang đến khả năng bảo vệ tối ưu mà vẫn đảm bảo an toàn cho da trẻ nhỏ:</p>\n<ul>\n<li>Titanium Dioxide và Kẽm Oxide: Bộ lọc vật lý an toàn, tạo nên lớp màng chống nắng khuếch tán và phản xạ UV để chúng không xuyên thấu vào da.</li>\n<li>Ectoin: “Lá chắn sinh học&#8221; bảo vệ da khỏi tia HEVL (ánh sáng xanh từ thiết bị điện tử) và IR-A (tia hồng ngoại).</li>\n</ul>\n<p>Khác hoàn toàn với kem chống nắng hóa học, kem chống nắng vật lý sẽ tại 1 lớp màng mỏng trên da để phản xạ lại các loại tia UV.</p>\n<h2>2. Dưỡng ẩm, làm dịu và ngăn ngừa khô da</h2>\n<p>Nuôi dưỡng da bằng những thành phần thiên nhiên lành tính:</p>\n<ul>\n<li>Chiết xuất cúc la mã: Làm dịu da, giảm kích ứng, mẩn đỏ, viêm da và hỗ trợ kháng khuẩn</li>\n<li>Vitamin E và vitamin B5: Cấp nước, khóa ẩm, tránh tình trạng khô da khi tiếp xúc với ánh nắng lâu dài</li>\n<li>Dầu Jojoba: Nuôi dưỡng &amp; tái tạo da luôn mềm mượt, tăng cường hàng rào bảo vệ da khỏe mạnh hơn mỗi ngày.</li>\n</ul>\n<h3>3. An toàn cho da trẻ nhỏ</h3>\n<p>Da trẻ nhỏ rất nhạy cảm với các hóa chất mạnh. Vì vậy, thành phần nguyên liệu của Dr.Anmytas IR3 không chứa các thành phần có nguy cơ gây hại cho cơ thể của trẻ nhỏ:</p>\n<ul>\n<li>Không kích thích hoocmon sinh trưởng, không gây u hạt/ ảnh hưởng tuyến giáp hay gây ung thư da</li>\n<li>Không cồn, Không hương liệu</li>\n<li>Không paraben</li>\n<li>Phù hợp cho trẻ từ 6 tháng tuổi trở lên</li>\n</ul>\n\n  \n    <div id=\"gallery-709229070\" class=\"row cus-image-gallery large-columns-3 medium-columns- small-columns-2 row-xsmall row-masonry\" data-packery-options='{\"itemSelector\": \".col\", \"gutter\": 0, \"presentageWidth\" : true}'>\n\n  <div class=\"gallery-col col\">\n          <div class=\"col-inner\">\n                        <div class=\"box has-hover gallery-box box-none\">\n              <div class=\"box-image\">\n                <img width=\"167\" height=\"300\" src=\"https://dranmytas.com/wp-content/uploads/2026/01/IR3-5-167x300.jpg\" class=\"cus-image-gallery\" alt=\"\" style=\"none\" />                                                              </div>\n              <div class=\"box-text text-left\">\n                 <p></p>\n              </div>\n            </div>\n                      </div>\n         </div><div class=\"gallery-col col\">\n          <div class=\"col-inner\">\n                        <div class=\"box has-hover gallery-box box-none\">\n              <div class=\"box-image\">\n                <img width=\"300\" height=\"300\" src=\"https://dranmytas.com/wp-content/uploads/2026/01/IR3-4-300x300.jpg\" class=\"cus-image-gallery\" alt=\"\" style=\"none\" />                                                              </div>\n              <div class=\"box-text text-left\">\n                 <p></p>\n              </div>\n            </div>\n                      </div>\n         </div><div class=\"gallery-col col\">\n          <div class=\"col-inner\">\n                        <div class=\"box has-hover gallery-box box-none\">\n              <div class=\"box-image\">\n                <img width=\"167\" height=\"300\" src=\"https://dranmytas.com/wp-content/uploads/2026/01/IR3-2-167x300.jpg\" class=\"cus-image-gallery\" alt=\"\" style=\"none\" />                                                              </div>\n              <div class=\"box-text text-left\">\n                 <p></p>\n              </div>\n            </div>\n                      </div>\n         </div><div class=\"gallery-col col\">\n          <div class=\"col-inner\">\n                        <div class=\"box has-hover gallery-box box-none\">\n              <div class=\"box-image\">\n                <img width=\"167\" height=\"300\" src=\"https://dranmytas.com/wp-content/uploads/2026/01/IR3-3-167x300.jpg\" class=\"cus-image-gallery\" alt=\"\" style=\"none\" />                                                              </div>\n              <div class=\"box-text text-left\">\n                 <p></p>\n              </div>\n            </div>\n                      </div>\n         </div><div class=\"gallery-col col\">\n          <div class=\"col-inner\">\n                        <div class=\"box has-hover gallery-box box-none\">\n              <div class=\"box-image\">\n                <img width=\"197\" height=\"300\" src=\"https://dranmytas.com/wp-content/uploads/2026/01/IR3-1-197x300.jpg\" class=\"cus-image-gallery\" alt=\"\" style=\"none\" />                                                              </div>\n              <div class=\"box-text text-left\">\n                 <p></p>\n              </div>\n            </div>\n                      </div>\n         </div></div>",
  "on_sale": false,
  "prices": {
    "price": "0",
    "regular_price": "0",
    "sale_price": "0",
    "price_range": null,
    "currency_code": "VND",
    "currency_symbol": "₫",
    "currency_minor_unit": 0,
    "currency_decimal_separator": ",",
    "currency_thousand_separator": ".",
    "currency_prefix": "",
    "currency_suffix": " ₫"
  },
  "price_html": "",
  "average_rating": "0",
  "review_count": 0,
  "images": [
    {
      "id": 2348,
      "src": "https://dranmytas.com/wp-content/uploads/2025/05/ir3.jpg",
      "thumbnail": "https://dranmytas.com/wp-content/uploads/2025/05/ir3-600x600.jpg",
      "srcset": "https://dranmytas.com/wp-content/uploads/2025/05/ir3.jpg 1200w, https://dranmytas.com/wp-content/uploads/2025/05/ir3-300x300.jpg 300w, https://dranmytas.com/wp-content/uploads/2025/05/ir3-1024x1024.jpg 1024w, https://dranmytas.com/wp-content/uploads/2025/05/ir3-150x150.jpg 150w, https://dranmytas.com/wp-content/uploads/2025/05/ir3-768x768.jpg 768w, https://dranmytas.com/wp-content/uploads/2025/05/ir3-600x600.jpg 600w, https://dranmytas.com/wp-content/uploads/2025/05/ir3-100x100.jpg 100w",
      "sizes": "(max-width: 1200px) 100vw, 1200px",
      "thumbnail_srcset": "https://dranmytas.com/wp-content/uploads/2025/05/ir3-600x600.jpg 600w, https://dranmytas.com/wp-content/uploads/2025/05/ir3-300x300.jpg 300w, https://dranmytas.com/wp-content/uploads/2025/05/ir3-1024x1024.jpg 1024w, https://dranmytas.com/wp-content/uploads/2025/05/ir3-150x150.jpg 150w, https://dranmytas.com/wp-content/uploads/2025/05/ir3-768x768.jpg 768w, https://dranmytas.com/wp-content/uploads/2025/05/ir3-100x100.jpg 100w, https://dranmytas.com/wp-content/uploads/2025/05/ir3.jpg 1200w",
      "thumbnail_sizes": "(max-width: 600px) 100vw, 600px",
      "name": "ir3",
      "alt": ""
    },
    {
      "id": 2391,
      "src": "https://dranmytas.com/wp-content/uploads/2025/05/tui-ir1-2.jpg",
      "thumbnail": "https://dranmytas.com/wp-content/uploads/2025/05/tui-ir1-2-600x600.jpg",
      "srcset": "https://dranmytas.com/wp-content/uploads/2025/05/tui-ir1-2.jpg 1200w, https://dranmytas.com/wp-content/uploads/2025/05/tui-ir1-2-300x300.jpg 300w, https://dranmytas.com/wp-content/uploads/2025/05/tui-ir1-2-1024x1024.jpg 1024w, https://dranmytas.com/wp-content/uploads/2025/05/tui-ir1-2-150x150.jpg 150w, https://dranmytas.com/wp-content/uploads/2025/05/tui-ir1-2-768x768.jpg 768w, https://dranmytas.com/wp-content/uploads/2025/05/tui-ir1-2-600x600.jpg 600w, https://dranmytas.com/wp-content/uploads/2025/05/tui-ir1-2-100x100.jpg 100w",
      "sizes": "(max-width: 1200px) 100vw, 1200px",
      "thumbnail_srcset": "https://dranmytas.com/wp-content/uploads/2025/05/tui-ir1-2-600x600.jpg 600w, https://dranmytas.com/wp-content/uploads/2025/05/tui-ir1-2-300x300.jpg 300w, https://dranmytas.com/wp-content/uploads/2025/05/tui-ir1-2-1024x1024.jpg 1024w, https://dranmytas.com/wp-content/uploads/2025/05/tui-ir1-2-150x150.jpg 150w, https://dranmytas.com/wp-content/uploads/2025/05/tui-ir1-2-768x768.jpg 768w, https://dranmytas.com/wp-content/uploads/2025/05/tui-ir1-2-100x100.jpg 100w, https://dranmytas.com/wp-content/uploads/2025/05/tui-ir1-2.jpg 1200w",
      "thumbnail_sizes": "(max-width: 600px) 100vw, 600px",
      "name": "tui-ir1 (2)",
      "alt": ""
    },
    {
      "id": 2994,
      "src": "https://dranmytas.com/wp-content/uploads/2025/10/Anh-chup-man-hinh-2025-11-21-093228.png",
      "thumbnail": "https://dranmytas.com/wp-content/uploads/2025/10/Anh-chup-man-hinh-2025-11-21-093228-600x781.png",
      "srcset": "https://dranmytas.com/wp-content/uploads/2025/10/Anh-chup-man-hinh-2025-11-21-093228.png 607w, https://dranmytas.com/wp-content/uploads/2025/10/Anh-chup-man-hinh-2025-11-21-093228-231x300.png 231w, https://dranmytas.com/wp-content/uploads/2025/10/Anh-chup-man-hinh-2025-11-21-093228-600x781.png 600w",
      "sizes": "(max-width: 607px) 100vw, 607px",
      "thumbnail_srcset": "https://dranmytas.com/wp-content/uploads/2025/10/Anh-chup-man-hinh-2025-11-21-093228-600x781.png 600w, https://dranmytas.com/wp-content/uploads/2025/10/Anh-chup-man-hinh-2025-11-21-093228-231x300.png 231w, https://dranmytas.com/wp-content/uploads/2025/10/Anh-chup-man-hinh-2025-11-21-093228.png 607w",
      "thumbnail_sizes": "(max-width: 600px) 100vw, 600px",
      "name": "Ảnh chụp màn hình 2025-11-21 093228",
      "alt": ""
    },
    {
      "id": 2993,
      "src": "https://dranmytas.com/wp-content/uploads/2025/10/Anh-chup-man-hinh-2025-11-21-093245.png",
      "thumbnail": "https://dranmytas.com/wp-content/uploads/2025/10/Anh-chup-man-hinh-2025-11-21-093245.png",
      "srcset": "https://dranmytas.com/wp-content/uploads/2025/10/Anh-chup-man-hinh-2025-11-21-093245.png 595w, https://dranmytas.com/wp-content/uploads/2025/10/Anh-chup-man-hinh-2025-11-21-093245-231x300.png 231w",
      "sizes": "(max-width: 595px) 100vw, 595px",
      "thumbnail_srcset": "https://dranmytas.com/wp-content/uploads/2025/10/Anh-chup-man-hinh-2025-11-21-093245.png 595w, https://dranmytas.com/wp-content/uploads/2025/10/Anh-chup-man-hinh-2025-11-21-093245-231x300.png 231w",
      "thumbnail_sizes": "(max-width: 595px) 100vw, 595px",
      "name": "Ảnh chụp màn hình 2025-11-21 093245",
      "alt": ""
    }
  ],
  "categories": [
    {
      "id": 111,
      "name": "Bảo vệ da",
      "slug": "bao-ve-da",
      "link": "https://dranmytas.com/product-category/bao-ve-da/"
    }
  ],
  "tags": [
    {
      "id": 115,
      "name": "A",
      "slug": "a",
      "link": "https://dranmytas.com/product-tag/a/"
    }
  ],
  "brands": [
    {
      "id": 105,
      "name": "Dr Anmytas",
      "slug": "dr-anmytas",
      "link": "https://dranmytas.com/thuong-hieu/dr-anmytas/"
    }
  ],
  "attributes": [],
  "variations": [],
  "grouped_products": [],
  "has_options": false,
  "is_purchasable": false,
  "is_in_stock": true,
  "is_on_backorder": false,
  "low_stock_remaining": null,
  "stock_availability": {
    "text": "",
    "class": "in-stock"
  },
  "sold_individually": false,
  "weight": "",
  "dimensions": {
    "length": "",
    "width": "",
    "height": ""
  },
  "formatted_weight": "Không áp dụng",
  "formatted_dimensions": "Không áp dụng",
  "add_to_cart": {
    "text": "Đọc tiếp",
    "description": "Đọc thêm về &ldquo;DR.ANMYTAS IR3&rdquo;",
    "url": "https://dranmytas.com/product/ir3/",
    "single_text": "Thêm vào giỏ hàng",
    "minimum": 1,
    "maximum": 9999,
    "multiple_of": 1
  },
  "is_password_protected": false,
  "extensions": {},
  "_links": {
    "self": [
      {
        "href": "https://dranmytas.com/wp-json/wc/store/v1/products/2408",
        "targetHints": {
          "allow": [
            "GET"
          ]
        }
      }
    ],
    "collection": [
      {
        "href": "https://dranmytas.com/wp-json/wc/store/v1/products"
      }
    ],
    "related": [
      {
        "embeddable": true,
        "href": "https://dranmytas.com/wp-json/wc/store/v1/products?related=2408&per_page=10"
      }
    ]
  }
}