{
  "id": 1741,
  "name": "FW5-BAOLIFT",
  "slug": "fw5-baolift",
  "parent": 0,
  "type": "simple",
  "variation": "",
  "permalink": "https://dranmytas.com/product/fw5-baolift/",
  "sku": "FW5",
  "short_description": "<p>Cơ chế sáng tạo lần đầu tiên trên thế giới xuất hiện trong mỹ phẩm giảm bọng mắt</p>",
  "description": "<h2>3 NGUYÊN NHÂN GÂY BỌNG MẮT NHƯ SAU:</h2>\n<ol>\n<li>Mất độ đàn hồi &amp; chảy xệ da do collagen &amp; elastin suy giảm, hệ thống cơ nâng đỡ suy yếu</li>\n<li>Tích tụ mỡ dưới da</li>\n<li>Ứ đọng dịch, tích nước và tuần hoàn kém</li>\n</ol>\n<h2>TÁC DỤNG FW5-BAOLIFT</h2>\n<h3>Săn chắc vùng da mắt và nọng cằm</h3>\n<p>Baolift giúp tăng sinh collagen, cải thiện cấu trúc nâng đỡ da. Baolift kích hoạt tế bào nguyên bào sợi, thúc đẩy tổng hợp collagen và elastin, giúp da đàn hồi và săn chắc hơn. Nhờ đó, vùng da dưới mắt và nọng cằm được củng cố độ đàn hồi, không còn lỏng lẻo hay chảy xệ.</p>\n<h3>Giảm mỡ vùng bọng mắt và nọng cằm</h3>\n<p>Baolift kích hoạt ty thể trong tế bào, làm tăng cường trao đổi chất. Khi năng lượng cơ thể tăng cao, quá trình đốt mỡ tự nhiên trong tế bào cũng tăng lên, giúp loại bỏ các mô mỡ dư thừa ở vùng cằm và bọng mắt.</p>\n<p>Hỗ trợ phá vỡ các tế bào mỡ, thúc đẩy sự phân giải mỡ dưới da, đặc biệt là những vùng tích tụ mỡ lâu năm như nọng cằm.</p>\n<h3>Giảm dịch ở vùng bọng mắt và nọng cằm</h3>\n<p>Baolift giúp tăng cường co cơ vòng mi và cơ vùng cằm, giúp cải thiện lưu thông dịch bạch huyết, loại bỏ nhanh chóng dịch mô kẽ tích tụ.</p>\n<p>Thúc đẩy năng lượng ty thể kích thích hoạt động của tế bào cơ, giúp các cơ co bóp mạnh mẽ hơn, hỗ trợ đào thải dịch dư thừa ở vùng bọng mắt và nọng cằm.</p>\n<p>Nhờ đó, tình trạng bọng mắt do tích nước giảm nhanh chóng, vùng cằm cũng gọn gàng hơn do giảm phù nề.</p>\n<h3>Ưu điểm sản phẩm</h3>\n<p>GIẢM 30% THỂ TÍCH BỌNG MẮT SAU 56 NGÀY</p>\n<p>Baolift sở hữu 3 giải thưởng quốc tế:</p>\n<ul>\n<li>Giải thưởng Thành phần Tốt nhất 2024 Toàn Cầu tai in-cosmetics global</li>\n<li>Giải thưởng Thành phần Hoạt tính Xuất sắc 2024 tai in-cosmetics Korea</li>\n<li>Giải Bạc Thành phần Hoạt tinh Xuất sắc 2024 Châu Á của in-cosmetics Asia</li>\n</ul>",
  "on_sale": false,
  "prices": {
    "price": "0",
    "regular_price": "0",
    "sale_price": "0",
    "price_range": null,
    "currency_code": "VND",
    "currency_symbol": "₫",
    "currency_minor_unit": 0,
    "currency_decimal_separator": ",",
    "currency_thousand_separator": ".",
    "currency_prefix": "",
    "currency_suffix": " ₫"
  },
  "price_html": "",
  "average_rating": "0",
  "review_count": 0,
  "images": [
    {
      "id": 2881,
      "src": "https://dranmytas.com/wp-content/uploads/2025/04/fw5-2.4-scaled.png",
      "thumbnail": "https://dranmytas.com/wp-content/uploads/2025/04/fw5-2.4-600x600.png",
      "srcset": "https://dranmytas.com/wp-content/uploads/2025/04/fw5-2.4-scaled.png 2560w, https://dranmytas.com/wp-content/uploads/2025/04/fw5-2.4-300x300.png 300w, https://dranmytas.com/wp-content/uploads/2025/04/fw5-2.4-1024x1024.png 1024w, https://dranmytas.com/wp-content/uploads/2025/04/fw5-2.4-150x150.png 150w, https://dranmytas.com/wp-content/uploads/2025/04/fw5-2.4-768x768.png 768w, https://dranmytas.com/wp-content/uploads/2025/04/fw5-2.4-1536x1536.png 1536w, https://dranmytas.com/wp-content/uploads/2025/04/fw5-2.4-2048x2048.png 2048w, https://dranmytas.com/wp-content/uploads/2025/04/fw5-2.4-600x600.png 600w, https://dranmytas.com/wp-content/uploads/2025/04/fw5-2.4-100x100.png 100w",
      "sizes": "(max-width: 2560px) 100vw, 2560px",
      "thumbnail_srcset": "https://dranmytas.com/wp-content/uploads/2025/04/fw5-2.4-600x600.png 600w, https://dranmytas.com/wp-content/uploads/2025/04/fw5-2.4-300x300.png 300w, https://dranmytas.com/wp-content/uploads/2025/04/fw5-2.4-1024x1024.png 1024w, https://dranmytas.com/wp-content/uploads/2025/04/fw5-2.4-150x150.png 150w, https://dranmytas.com/wp-content/uploads/2025/04/fw5-2.4-768x768.png 768w, https://dranmytas.com/wp-content/uploads/2025/04/fw5-2.4-1536x1536.png 1536w, https://dranmytas.com/wp-content/uploads/2025/04/fw5-2.4-2048x2048.png 2048w, https://dranmytas.com/wp-content/uploads/2025/04/fw5-2.4-100x100.png 100w",
      "thumbnail_sizes": "(max-width: 600px) 100vw, 600px",
      "name": "fw5 2.4",
      "alt": ""
    },
    {
      "id": 2944,
      "src": "https://dranmytas.com/wp-content/uploads/2025/04/fw5-new-8-scaled.png",
      "thumbnail": "https://dranmytas.com/wp-content/uploads/2025/04/fw5-new-8-600x600.png",
      "srcset": "https://dranmytas.com/wp-content/uploads/2025/04/fw5-new-8-scaled.png 2560w, https://dranmytas.com/wp-content/uploads/2025/04/fw5-new-8-300x300.png 300w, https://dranmytas.com/wp-content/uploads/2025/04/fw5-new-8-1024x1024.png 1024w, https://dranmytas.com/wp-content/uploads/2025/04/fw5-new-8-150x150.png 150w, https://dranmytas.com/wp-content/uploads/2025/04/fw5-new-8-768x768.png 768w, https://dranmytas.com/wp-content/uploads/2025/04/fw5-new-8-1536x1536.png 1536w, https://dranmytas.com/wp-content/uploads/2025/04/fw5-new-8-2048x2048.png 2048w, https://dranmytas.com/wp-content/uploads/2025/04/fw5-new-8-600x600.png 600w, https://dranmytas.com/wp-content/uploads/2025/04/fw5-new-8-100x100.png 100w",
      "sizes": "(max-width: 2560px) 100vw, 2560px",
      "thumbnail_srcset": "https://dranmytas.com/wp-content/uploads/2025/04/fw5-new-8-600x600.png 600w, https://dranmytas.com/wp-content/uploads/2025/04/fw5-new-8-300x300.png 300w, https://dranmytas.com/wp-content/uploads/2025/04/fw5-new-8-1024x1024.png 1024w, https://dranmytas.com/wp-content/uploads/2025/04/fw5-new-8-150x150.png 150w, https://dranmytas.com/wp-content/uploads/2025/04/fw5-new-8-768x768.png 768w, https://dranmytas.com/wp-content/uploads/2025/04/fw5-new-8-1536x1536.png 1536w, https://dranmytas.com/wp-content/uploads/2025/04/fw5-new-8-2048x2048.png 2048w, https://dranmytas.com/wp-content/uploads/2025/04/fw5-new-8-100x100.png 100w",
      "thumbnail_sizes": "(max-width: 600px) 100vw, 600px",
      "name": "fw5 new 8",
      "alt": ""
    },
    {
      "id": 2941,
      "src": "https://dranmytas.com/wp-content/uploads/2025/04/fw5-new-2.1.png",
      "thumbnail": "https://dranmytas.com/wp-content/uploads/2025/04/fw5-new-2.1-600x600.png",
      "srcset": "https://dranmytas.com/wp-content/uploads/2025/04/fw5-new-2.1.png 2000w, https://dranmytas.com/wp-content/uploads/2025/04/fw5-new-2.1-300x300.png 300w, https://dranmytas.com/wp-content/uploads/2025/04/fw5-new-2.1-1024x1024.png 1024w, https://dranmytas.com/wp-content/uploads/2025/04/fw5-new-2.1-150x150.png 150w, https://dranmytas.com/wp-content/uploads/2025/04/fw5-new-2.1-768x768.png 768w, https://dranmytas.com/wp-content/uploads/2025/04/fw5-new-2.1-1536x1536.png 1536w, https://dranmytas.com/wp-content/uploads/2025/04/fw5-new-2.1-600x600.png 600w, https://dranmytas.com/wp-content/uploads/2025/04/fw5-new-2.1-100x100.png 100w",
      "sizes": "(max-width: 2000px) 100vw, 2000px",
      "thumbnail_srcset": "https://dranmytas.com/wp-content/uploads/2025/04/fw5-new-2.1-600x600.png 600w, https://dranmytas.com/wp-content/uploads/2025/04/fw5-new-2.1-300x300.png 300w, https://dranmytas.com/wp-content/uploads/2025/04/fw5-new-2.1-1024x1024.png 1024w, https://dranmytas.com/wp-content/uploads/2025/04/fw5-new-2.1-150x150.png 150w, https://dranmytas.com/wp-content/uploads/2025/04/fw5-new-2.1-768x768.png 768w, https://dranmytas.com/wp-content/uploads/2025/04/fw5-new-2.1-1536x1536.png 1536w, https://dranmytas.com/wp-content/uploads/2025/04/fw5-new-2.1-100x100.png 100w, https://dranmytas.com/wp-content/uploads/2025/04/fw5-new-2.1.png 2000w",
      "thumbnail_sizes": "(max-width: 600px) 100vw, 600px",
      "name": "fw5 new 2.1",
      "alt": ""
    },
    {
      "id": 2942,
      "src": "https://dranmytas.com/wp-content/uploads/2025/04/fw5-new-2.2.png",
      "thumbnail": "https://dranmytas.com/wp-content/uploads/2025/04/fw5-new-2.2-600x600.png",
      "srcset": "https://dranmytas.com/wp-content/uploads/2025/04/fw5-new-2.2.png 2000w, https://dranmytas.com/wp-content/uploads/2025/04/fw5-new-2.2-300x300.png 300w, https://dranmytas.com/wp-content/uploads/2025/04/fw5-new-2.2-1024x1024.png 1024w, https://dranmytas.com/wp-content/uploads/2025/04/fw5-new-2.2-150x150.png 150w, https://dranmytas.com/wp-content/uploads/2025/04/fw5-new-2.2-768x768.png 768w, https://dranmytas.com/wp-content/uploads/2025/04/fw5-new-2.2-1536x1536.png 1536w, https://dranmytas.com/wp-content/uploads/2025/04/fw5-new-2.2-600x600.png 600w, https://dranmytas.com/wp-content/uploads/2025/04/fw5-new-2.2-100x100.png 100w",
      "sizes": "(max-width: 2000px) 100vw, 2000px",
      "thumbnail_srcset": "https://dranmytas.com/wp-content/uploads/2025/04/fw5-new-2.2-600x600.png 600w, https://dranmytas.com/wp-content/uploads/2025/04/fw5-new-2.2-300x300.png 300w, https://dranmytas.com/wp-content/uploads/2025/04/fw5-new-2.2-1024x1024.png 1024w, https://dranmytas.com/wp-content/uploads/2025/04/fw5-new-2.2-150x150.png 150w, https://dranmytas.com/wp-content/uploads/2025/04/fw5-new-2.2-768x768.png 768w, https://dranmytas.com/wp-content/uploads/2025/04/fw5-new-2.2-1536x1536.png 1536w, https://dranmytas.com/wp-content/uploads/2025/04/fw5-new-2.2-100x100.png 100w, https://dranmytas.com/wp-content/uploads/2025/04/fw5-new-2.2.png 2000w",
      "thumbnail_sizes": "(max-width: 600px) 100vw, 600px",
      "name": "fw5 new 2.2",
      "alt": ""
    }
  ],
  "categories": [
    {
      "id": 126,
      "name": "Sản phẩm DR.ANMYTAS",
      "slug": "san-pham-dr-anmytas",
      "link": "https://dranmytas.com/product-category/san-pham-dr-anmytas/"
    },
    {
      "id": 109,
      "name": "Chăm sóc vùng da mắt",
      "slug": "cham-soc-vung-da-mat",
      "link": "https://dranmytas.com/product-category/cham-soc-vung-da-mat/"
    }
  ],
  "tags": [],
  "brands": [
    {
      "id": 105,
      "name": "Dr Anmytas",
      "slug": "dr-anmytas",
      "link": "https://dranmytas.com/thuong-hieu/dr-anmytas/"
    }
  ],
  "attributes": [],
  "variations": [],
  "grouped_products": [],
  "has_options": false,
  "is_purchasable": false,
  "is_in_stock": true,
  "is_on_backorder": false,
  "low_stock_remaining": null,
  "stock_availability": {
    "text": "",
    "class": "in-stock"
  },
  "sold_individually": false,
  "weight": "",
  "dimensions": {
    "length": "",
    "width": "",
    "height": ""
  },
  "formatted_weight": "Không áp dụng",
  "formatted_dimensions": "Không áp dụng",
  "add_to_cart": {
    "text": "Đọc tiếp",
    "description": "Đọc thêm về &ldquo;FW5-BAOLIFT&rdquo;",
    "url": "https://dranmytas.com/product/fw5-baolift/",
    "single_text": "Thêm vào giỏ hàng",
    "minimum": 1,
    "maximum": 9999,
    "multiple_of": 1
  },
  "is_password_protected": false,
  "extensions": {},
  "_links": {
    "self": [
      {
        "href": "https://dranmytas.com/wp-json/wc/store/v1/products/1741",
        "targetHints": {
          "allow": [
            "GET"
          ]
        }
      }
    ],
    "collection": [
      {
        "href": "https://dranmytas.com/wp-json/wc/store/v1/products"
      }
    ],
    "related": [
      {
        "embeddable": true,
        "href": "https://dranmytas.com/wp-json/wc/store/v1/products?related=1741&per_page=10"
      }
    ]
  }
}