{
  "id": 1101,
  "name": "SỮA RỬA MẶT SALIPO-1",
  "slug": "salipo-1",
  "parent": 0,
  "type": "simple",
  "variation": "",
  "permalink": "https://dranmytas.com/product/salipo-1/",
  "sku": "",
  "short_description": "<p>Sữa rửa mặt chuyên biệt dành cho da dầu mụn: Thanh lọc bụi bẩn, dầu thừa, tế bào chết từ sâu trong lỗ chân lông và hỗ trợ giảm mụn hiệu quả</p>",
  "description": "<h2>NGUỒN GỐC NGUYÊN LIỆU CHÍNH</h2>\n<ul>\n<li>Acid Salicylic đến từ Alban Mullet &#8211; Pháp</li>\n<li>Seppic &#8211; Pháp</li>\n<li>Cisme &#8211; Ý</li>\n<li>Primient Covation &#8211; Mỹ</li>\n</ul>\n<h2>ƯU ĐIỂM SẢN PHẨM:</h2>\n<p>Chứa Acid Salicylic đẳng cấp đến từ Pháp</p>\n<h2>LỢI ÍCH:</h2>\n<h3>Làm sạch sâu lỗ chân lông</h3>\n<p>Salicylic Acid là một loại BHA có khả năng tan trong dầu, dễ dàng thâm nhập vào sâu trong lỗ chân lông để loại bỏ bụi bẩn, bã nhờn và tế bào chết tích tụ.<br />\nViệc làm sạch sâu này giúp lỗ chân lông thông thoáng hơn, hạn chế tình trạng bít tắc &#8211; nguyên nhân chính gây ra mụn.</p>\n<h3>Hỗ trợ giảm vi khuẩn gây mụn</h3>\n<p>Sữa rửa mặt chứa Salicylic Acid chiết xuất từ cây Lộc Đề cao cấp, có đặc tính giảm vi khuẩn bám trên da và kháng viêm nhẹ, hỗ trợ ngăn ngừa sự phát triển của vi khuẩn gây mụn như Pr.acnes. Giúp giảm sưng đỏ và làm dịu các nốt mụn viêm trên da, giúp da hồi phục nhanh hơn mà không gây kích ứng mạnh.</p>\n<h3>Kiểm soát bã nhờn hiệu quả</h3>\n<p>Salicylic Acid hỗ trợ điều tiết lượng dầu trên da, làm giảm tình trạng bóng nhờn nhưng không làm khô da.<br />\nViệc kiểm soát bã nhờn cũng giúp ngăn ngừa nguy cơ mụn tái phát, giữ cho da luôn ở trạng thái sạch sẽ, thoáng mát.</p>\n<h3>Tẩy tế bào chết nhẹ nhàng, se khít lỗ chân lông</h3>\n<p>BHA giúp loại bỏ tế bào da chết trên bề mặt, ngăn ngừa sự hình thành lớp sừng dày gây tắc nghẽn lỗ chân lông.<br />\nNhờ khả năng làm sạch và loại bỏ bã nhờn tích tụ, Salicylic Acid giúp giảm kích thước lỗ chân lông, làm cho da mịn màng và săn chắc hơn.</p>\n<h3>Ngăn ngừa và hỗ trợ chăm sóc da mụn</h3>\n<p>Salipo giúp ngăn ngừa mụn đầu đen, mụn đầu trắng và hạn chế mụn viêm. Nhờ khả năng làm sạch sâu, thành phần này giúp đẩy nhanh quá trình khô cồi mụn và ngăn ngừa mụn quay trở lại. Đặc biệt, hỗ trợ tốt cho da đang trong quá trình điều trị mụn, giảm thiểu tình trạng mụn tái phát.</p>\n<h3>Giúp làm đều màu da, giảm thâm sau mụn</h3>\n<p>Quá trình tẩy tế bào chết từ BHA giúp cải thiện sắc tố da, giảm thiểu các vết thâm mụn và đốm nâu, giúp da sáng đều màu hơn. Hỗ trợ ngăn ngừa sự hình thành các vết thâm mụn sau khi lành, giữ cho da luôn tươi sáng.</p>\n\n  \n    <div class=\"row large-columns-3 medium-columns- small-columns-2 row-xsmall\">\n  <div class=\"gallery-col col\">\n          <div class=\"col-inner\">\n                        <div class=\"box has-hover gallery-box box-none\">\n              <div class=\"box-image\">\n                <img width=\"200\" height=\"300\" src=\"https://dranmytas.com/wp-content/uploads/2025/04/salipo-1-4-200x300.jpg\" class=\"attachment-medium size-medium\" alt=\"\" style=\"none\" />                                                              </div>\n              <div class=\"box-text text-left\">\n                 <p></p>\n              </div>\n            </div>\n                      </div>\n         </div><div class=\"gallery-col col\">\n          <div class=\"col-inner\">\n                        <div class=\"box has-hover gallery-box box-none\">\n              <div class=\"box-image\">\n                <img width=\"200\" height=\"300\" src=\"https://dranmytas.com/wp-content/uploads/2025/04/salipo-1-1-200x300.jpg\" class=\"attachment-medium size-medium\" alt=\"\" style=\"none\" />                                                              </div>\n              <div class=\"box-text text-left\">\n                 <p></p>\n              </div>\n            </div>\n                      </div>\n         </div><div class=\"gallery-col col\">\n          <div class=\"col-inner\">\n                        <div class=\"box has-hover gallery-box box-none\">\n              <div class=\"box-image\">\n                <img width=\"200\" height=\"300\" src=\"https://dranmytas.com/wp-content/uploads/2025/04/salipo-1-2-200x300.jpg\" class=\"attachment-medium size-medium\" alt=\"\" style=\"none\" />                                                              </div>\n              <div class=\"box-text text-left\">\n                 <p></p>\n              </div>\n            </div>\n                      </div>\n         </div></div>",
  "on_sale": false,
  "prices": {
    "price": "0",
    "regular_price": "0",
    "sale_price": "0",
    "price_range": null,
    "currency_code": "VND",
    "currency_symbol": "₫",
    "currency_minor_unit": 0,
    "currency_decimal_separator": ",",
    "currency_thousand_separator": ".",
    "currency_prefix": "",
    "currency_suffix": " ₫"
  },
  "price_html": "",
  "average_rating": "0",
  "review_count": 0,
  "images": [
    {
      "id": 2847,
      "src": "https://dranmytas.com/wp-content/uploads/2025/08/salipo-1.2.2.jpg",
      "thumbnail": "https://dranmytas.com/wp-content/uploads/2025/08/salipo-1.2.2-600x600.jpg",
      "srcset": "https://dranmytas.com/wp-content/uploads/2025/08/salipo-1.2.2.jpg 1200w, https://dranmytas.com/wp-content/uploads/2025/08/salipo-1.2.2-300x300.jpg 300w, https://dranmytas.com/wp-content/uploads/2025/08/salipo-1.2.2-1024x1024.jpg 1024w, https://dranmytas.com/wp-content/uploads/2025/08/salipo-1.2.2-150x150.jpg 150w, https://dranmytas.com/wp-content/uploads/2025/08/salipo-1.2.2-768x768.jpg 768w, https://dranmytas.com/wp-content/uploads/2025/08/salipo-1.2.2-600x600.jpg 600w, https://dranmytas.com/wp-content/uploads/2025/08/salipo-1.2.2-100x100.jpg 100w",
      "sizes": "(max-width: 1200px) 100vw, 1200px",
      "thumbnail_srcset": "https://dranmytas.com/wp-content/uploads/2025/08/salipo-1.2.2-600x600.jpg 600w, https://dranmytas.com/wp-content/uploads/2025/08/salipo-1.2.2-300x300.jpg 300w, https://dranmytas.com/wp-content/uploads/2025/08/salipo-1.2.2-1024x1024.jpg 1024w, https://dranmytas.com/wp-content/uploads/2025/08/salipo-1.2.2-150x150.jpg 150w, https://dranmytas.com/wp-content/uploads/2025/08/salipo-1.2.2-768x768.jpg 768w, https://dranmytas.com/wp-content/uploads/2025/08/salipo-1.2.2-100x100.jpg 100w, https://dranmytas.com/wp-content/uploads/2025/08/salipo-1.2.2.jpg 1200w",
      "thumbnail_sizes": "(max-width: 600px) 100vw, 600px",
      "name": "salipo 1.2.2",
      "alt": ""
    },
    {
      "id": 2849,
      "src": "https://dranmytas.com/wp-content/uploads/2025/08/salipo-2.2.jpg",
      "thumbnail": "https://dranmytas.com/wp-content/uploads/2025/08/salipo-2.2-600x600.jpg",
      "srcset": "https://dranmytas.com/wp-content/uploads/2025/08/salipo-2.2.jpg 1200w, https://dranmytas.com/wp-content/uploads/2025/08/salipo-2.2-300x300.jpg 300w, https://dranmytas.com/wp-content/uploads/2025/08/salipo-2.2-1024x1024.jpg 1024w, https://dranmytas.com/wp-content/uploads/2025/08/salipo-2.2-150x150.jpg 150w, https://dranmytas.com/wp-content/uploads/2025/08/salipo-2.2-768x768.jpg 768w, https://dranmytas.com/wp-content/uploads/2025/08/salipo-2.2-600x600.jpg 600w, https://dranmytas.com/wp-content/uploads/2025/08/salipo-2.2-100x100.jpg 100w",
      "sizes": "(max-width: 1200px) 100vw, 1200px",
      "thumbnail_srcset": "https://dranmytas.com/wp-content/uploads/2025/08/salipo-2.2-600x600.jpg 600w, https://dranmytas.com/wp-content/uploads/2025/08/salipo-2.2-300x300.jpg 300w, https://dranmytas.com/wp-content/uploads/2025/08/salipo-2.2-1024x1024.jpg 1024w, https://dranmytas.com/wp-content/uploads/2025/08/salipo-2.2-150x150.jpg 150w, https://dranmytas.com/wp-content/uploads/2025/08/salipo-2.2-768x768.jpg 768w, https://dranmytas.com/wp-content/uploads/2025/08/salipo-2.2-100x100.jpg 100w, https://dranmytas.com/wp-content/uploads/2025/08/salipo-2.2.jpg 1200w",
      "thumbnail_sizes": "(max-width: 600px) 100vw, 600px",
      "name": "salipo 2.2",
      "alt": ""
    },
    {
      "id": 2848,
      "src": "https://dranmytas.com/wp-content/uploads/2025/08/salipo-1.6.jpg",
      "thumbnail": "https://dranmytas.com/wp-content/uploads/2025/08/salipo-1.6-600x600.jpg",
      "srcset": "https://dranmytas.com/wp-content/uploads/2025/08/salipo-1.6.jpg 1200w, https://dranmytas.com/wp-content/uploads/2025/08/salipo-1.6-300x300.jpg 300w, https://dranmytas.com/wp-content/uploads/2025/08/salipo-1.6-1024x1024.jpg 1024w, https://dranmytas.com/wp-content/uploads/2025/08/salipo-1.6-150x150.jpg 150w, https://dranmytas.com/wp-content/uploads/2025/08/salipo-1.6-768x768.jpg 768w, https://dranmytas.com/wp-content/uploads/2025/08/salipo-1.6-600x600.jpg 600w, https://dranmytas.com/wp-content/uploads/2025/08/salipo-1.6-100x100.jpg 100w",
      "sizes": "(max-width: 1200px) 100vw, 1200px",
      "thumbnail_srcset": "https://dranmytas.com/wp-content/uploads/2025/08/salipo-1.6-600x600.jpg 600w, https://dranmytas.com/wp-content/uploads/2025/08/salipo-1.6-300x300.jpg 300w, https://dranmytas.com/wp-content/uploads/2025/08/salipo-1.6-1024x1024.jpg 1024w, https://dranmytas.com/wp-content/uploads/2025/08/salipo-1.6-150x150.jpg 150w, https://dranmytas.com/wp-content/uploads/2025/08/salipo-1.6-768x768.jpg 768w, https://dranmytas.com/wp-content/uploads/2025/08/salipo-1.6-100x100.jpg 100w, https://dranmytas.com/wp-content/uploads/2025/08/salipo-1.6.jpg 1200w",
      "thumbnail_sizes": "(max-width: 600px) 100vw, 600px",
      "name": "salipo 1.6",
      "alt": ""
    },
    {
      "id": 2383,
      "src": "https://dranmytas.com/wp-content/uploads/2025/05/salipo1-3.jpg",
      "thumbnail": "https://dranmytas.com/wp-content/uploads/2025/05/salipo1-3-600x600.jpg",
      "srcset": "https://dranmytas.com/wp-content/uploads/2025/05/salipo1-3.jpg 1200w, https://dranmytas.com/wp-content/uploads/2025/05/salipo1-3-300x300.jpg 300w, https://dranmytas.com/wp-content/uploads/2025/05/salipo1-3-1024x1024.jpg 1024w, https://dranmytas.com/wp-content/uploads/2025/05/salipo1-3-150x150.jpg 150w, https://dranmytas.com/wp-content/uploads/2025/05/salipo1-3-768x768.jpg 768w, https://dranmytas.com/wp-content/uploads/2025/05/salipo1-3-600x600.jpg 600w, https://dranmytas.com/wp-content/uploads/2025/05/salipo1-3-100x100.jpg 100w",
      "sizes": "(max-width: 1200px) 100vw, 1200px",
      "thumbnail_srcset": "https://dranmytas.com/wp-content/uploads/2025/05/salipo1-3-600x600.jpg 600w, https://dranmytas.com/wp-content/uploads/2025/05/salipo1-3-300x300.jpg 300w, https://dranmytas.com/wp-content/uploads/2025/05/salipo1-3-1024x1024.jpg 1024w, https://dranmytas.com/wp-content/uploads/2025/05/salipo1-3-150x150.jpg 150w, https://dranmytas.com/wp-content/uploads/2025/05/salipo1-3-768x768.jpg 768w, https://dranmytas.com/wp-content/uploads/2025/05/salipo1-3-100x100.jpg 100w, https://dranmytas.com/wp-content/uploads/2025/05/salipo1-3.jpg 1200w",
      "thumbnail_sizes": "(max-width: 600px) 100vw, 600px",
      "name": "salipo1 (3)",
      "alt": ""
    },
    {
      "id": 2850,
      "src": "https://dranmytas.com/wp-content/uploads/2025/08/vo-hop-salipo-1-1.1.jpg",
      "thumbnail": "https://dranmytas.com/wp-content/uploads/2025/08/vo-hop-salipo-1-1.1-600x600.jpg",
      "srcset": "https://dranmytas.com/wp-content/uploads/2025/08/vo-hop-salipo-1-1.1.jpg 1200w, https://dranmytas.com/wp-content/uploads/2025/08/vo-hop-salipo-1-1.1-300x300.jpg 300w, https://dranmytas.com/wp-content/uploads/2025/08/vo-hop-salipo-1-1.1-1024x1024.jpg 1024w, https://dranmytas.com/wp-content/uploads/2025/08/vo-hop-salipo-1-1.1-150x150.jpg 150w, https://dranmytas.com/wp-content/uploads/2025/08/vo-hop-salipo-1-1.1-768x768.jpg 768w, https://dranmytas.com/wp-content/uploads/2025/08/vo-hop-salipo-1-1.1-600x600.jpg 600w, https://dranmytas.com/wp-content/uploads/2025/08/vo-hop-salipo-1-1.1-100x100.jpg 100w",
      "sizes": "(max-width: 1200px) 100vw, 1200px",
      "thumbnail_srcset": "https://dranmytas.com/wp-content/uploads/2025/08/vo-hop-salipo-1-1.1-600x600.jpg 600w, https://dranmytas.com/wp-content/uploads/2025/08/vo-hop-salipo-1-1.1-300x300.jpg 300w, https://dranmytas.com/wp-content/uploads/2025/08/vo-hop-salipo-1-1.1-1024x1024.jpg 1024w, https://dranmytas.com/wp-content/uploads/2025/08/vo-hop-salipo-1-1.1-150x150.jpg 150w, https://dranmytas.com/wp-content/uploads/2025/08/vo-hop-salipo-1-1.1-768x768.jpg 768w, https://dranmytas.com/wp-content/uploads/2025/08/vo-hop-salipo-1-1.1-100x100.jpg 100w, https://dranmytas.com/wp-content/uploads/2025/08/vo-hop-salipo-1-1.1.jpg 1200w",
      "thumbnail_sizes": "(max-width: 600px) 100vw, 600px",
      "name": "vo hop salipo 1 1.1",
      "alt": ""
    },
    {
      "id": 2851,
      "src": "https://dranmytas.com/wp-content/uploads/2025/08/vo-hop-salipo-1-1.2.jpg",
      "thumbnail": "https://dranmytas.com/wp-content/uploads/2025/08/vo-hop-salipo-1-1.2-600x600.jpg",
      "srcset": "https://dranmytas.com/wp-content/uploads/2025/08/vo-hop-salipo-1-1.2.jpg 1200w, https://dranmytas.com/wp-content/uploads/2025/08/vo-hop-salipo-1-1.2-300x300.jpg 300w, https://dranmytas.com/wp-content/uploads/2025/08/vo-hop-salipo-1-1.2-1024x1024.jpg 1024w, https://dranmytas.com/wp-content/uploads/2025/08/vo-hop-salipo-1-1.2-150x150.jpg 150w, https://dranmytas.com/wp-content/uploads/2025/08/vo-hop-salipo-1-1.2-768x768.jpg 768w, https://dranmytas.com/wp-content/uploads/2025/08/vo-hop-salipo-1-1.2-600x600.jpg 600w, https://dranmytas.com/wp-content/uploads/2025/08/vo-hop-salipo-1-1.2-100x100.jpg 100w",
      "sizes": "(max-width: 1200px) 100vw, 1200px",
      "thumbnail_srcset": "https://dranmytas.com/wp-content/uploads/2025/08/vo-hop-salipo-1-1.2-600x600.jpg 600w, https://dranmytas.com/wp-content/uploads/2025/08/vo-hop-salipo-1-1.2-300x300.jpg 300w, https://dranmytas.com/wp-content/uploads/2025/08/vo-hop-salipo-1-1.2-1024x1024.jpg 1024w, https://dranmytas.com/wp-content/uploads/2025/08/vo-hop-salipo-1-1.2-150x150.jpg 150w, https://dranmytas.com/wp-content/uploads/2025/08/vo-hop-salipo-1-1.2-768x768.jpg 768w, https://dranmytas.com/wp-content/uploads/2025/08/vo-hop-salipo-1-1.2-100x100.jpg 100w, https://dranmytas.com/wp-content/uploads/2025/08/vo-hop-salipo-1-1.2.jpg 1200w",
      "thumbnail_sizes": "(max-width: 600px) 100vw, 600px",
      "name": "vo hop salipo 1 1.2",
      "alt": ""
    },
    {
      "id": 2843,
      "src": "https://dranmytas.com/wp-content/uploads/2025/08/vo-hop-salipo-1-1.3.jpg",
      "thumbnail": "https://dranmytas.com/wp-content/uploads/2025/08/vo-hop-salipo-1-1.3-600x600.jpg",
      "srcset": "https://dranmytas.com/wp-content/uploads/2025/08/vo-hop-salipo-1-1.3.jpg 1200w, https://dranmytas.com/wp-content/uploads/2025/08/vo-hop-salipo-1-1.3-300x300.jpg 300w, https://dranmytas.com/wp-content/uploads/2025/08/vo-hop-salipo-1-1.3-1024x1024.jpg 1024w, https://dranmytas.com/wp-content/uploads/2025/08/vo-hop-salipo-1-1.3-150x150.jpg 150w, https://dranmytas.com/wp-content/uploads/2025/08/vo-hop-salipo-1-1.3-768x768.jpg 768w, https://dranmytas.com/wp-content/uploads/2025/08/vo-hop-salipo-1-1.3-600x600.jpg 600w, https://dranmytas.com/wp-content/uploads/2025/08/vo-hop-salipo-1-1.3-100x100.jpg 100w",
      "sizes": "(max-width: 1200px) 100vw, 1200px",
      "thumbnail_srcset": "https://dranmytas.com/wp-content/uploads/2025/08/vo-hop-salipo-1-1.3-600x600.jpg 600w, https://dranmytas.com/wp-content/uploads/2025/08/vo-hop-salipo-1-1.3-300x300.jpg 300w, https://dranmytas.com/wp-content/uploads/2025/08/vo-hop-salipo-1-1.3-1024x1024.jpg 1024w, https://dranmytas.com/wp-content/uploads/2025/08/vo-hop-salipo-1-1.3-150x150.jpg 150w, https://dranmytas.com/wp-content/uploads/2025/08/vo-hop-salipo-1-1.3-768x768.jpg 768w, https://dranmytas.com/wp-content/uploads/2025/08/vo-hop-salipo-1-1.3-100x100.jpg 100w, https://dranmytas.com/wp-content/uploads/2025/08/vo-hop-salipo-1-1.3.jpg 1200w",
      "thumbnail_sizes": "(max-width: 600px) 100vw, 600px",
      "name": "vo hop salipo 1 1.3",
      "alt": ""
    }
  ],
  "categories": [
    {
      "id": 126,
      "name": "Sản phẩm DR.ANMYTAS",
      "slug": "san-pham-dr-anmytas",
      "link": "https://dranmytas.com/product-category/san-pham-dr-anmytas/"
    }
  ],
  "tags": [
    {
      "id": 115,
      "name": "A",
      "slug": "a",
      "link": "https://dranmytas.com/product-tag/a/"
    }
  ],
  "brands": [
    {
      "id": 105,
      "name": "Dr Anmytas",
      "slug": "dr-anmytas",
      "link": "https://dranmytas.com/thuong-hieu/dr-anmytas/"
    }
  ],
  "attributes": [],
  "variations": [],
  "grouped_products": [],
  "has_options": false,
  "is_purchasable": false,
  "is_in_stock": true,
  "is_on_backorder": false,
  "low_stock_remaining": null,
  "stock_availability": {
    "text": "",
    "class": "in-stock"
  },
  "sold_individually": false,
  "weight": "",
  "dimensions": {
    "length": "",
    "width": "",
    "height": ""
  },
  "formatted_weight": "Không áp dụng",
  "formatted_dimensions": "Không áp dụng",
  "add_to_cart": {
    "text": "Đọc tiếp",
    "description": "Đọc thêm về &ldquo;SỮA RỬA MẶT SALIPO-1&rdquo;",
    "url": "https://dranmytas.com/product/salipo-1/",
    "single_text": "Thêm vào giỏ hàng",
    "minimum": 1,
    "maximum": 9999,
    "multiple_of": 1
  },
  "is_password_protected": false,
  "extensions": {},
  "_links": {
    "self": [
      {
        "href": "https://dranmytas.com/wp-json/wc/store/v1/products/1101",
        "targetHints": {
          "allow": [
            "GET"
          ]
        }
      }
    ],
    "collection": [
      {
        "href": "https://dranmytas.com/wp-json/wc/store/v1/products"
      }
    ],
    "related": [
      {
        "embeddable": true,
        "href": "https://dranmytas.com/wp-json/wc/store/v1/products?related=1101&per_page=10"
      }
    ]
  }
}